README.md
rerank.py
setup.py
torchrerank
pytorch_rerank.egg-info/PKG-INFO
pytorch_rerank.egg-info/SOURCES.txt
pytorch_rerank.egg-info/dependency_links.txt
pytorch_rerank.egg-info/requires.txt
pytorch_rerank.egg-info/top_level.txt