Metadata-Version: 2.1
Name: pytorch-rerank
Version: 0.1.2
Summary: A simple distributed script to modify container RANK envs for pytorch training jobs
Home-page: http://gitlab.alibaba-inc.com/tre-ai-infra/pytorch_rerank.git
Author: wenhuhu
Author-email: huwenhu.hwh@alibaba-inc.com
License: UNKNOWN
Platform: UNKNOWN
Classifier: Programming Language :: Python :: 3
Classifier: License :: OSI Approved :: MIT License
Classifier: Operating System :: OS Independent
Requires-Python: >=3.6
